{
  "root" : "HEAD_TERM",
  "score" : 0.0,
  "linkScore" : 0.0,
  "children" : [ {
    "root" : "country",
    "score" : 0.12128343148130073,
    "linkScore" : "NaN",
    "children" : [ {
      "root" : "manufacturing",
      "score" : 0.0814005868581418,
      "linkScore" : 0.9207535518963933,
      "children" : [ ],
      "status" : "none",
      "parent" : null
    }, {
      "root" : "deficit reduction",
      "score" : 0.09659432716124709,
      "linkScore" : 0.920132692961144,
      "children" : [ ],
      "status" : "none",
      "parent" : null
    }, {
      "root" : "income",
      "score" : 0.06646307108711931,
      "linkScore" : 0.680426723545752,
      "children" : [ ],
      "status" : "none",
      "parent" : null
    }, {
      "root" : "Americans",
      "score" : 0.1497339540500975,
      "linkScore" : 0.29898849890587503,
      "children" : [ ],
      "status" : "none",
      "parent" : null
    } ],
    "status" : "none",
    "parent" : null
  }, {
    "root" : "security",
    "score" : 0.1536510042150771,
    "linkScore" : "NaN",
    "children" : [ {
      "root" : "insurance",
      "score" : 0.09244719647781051,
      "linkScore" : 0.9999934296753203,
      "children" : [ ],
      "status" : "none",
      "parent" : null
    }, {
      "root" : "health insurance",
      "score" : 0.13112697637658888,
      "linkScore" : 0.9999513461273115,
      "children" : [ ],
      "status" : "none",
      "parent" : null
    } ],
    "status" : "none",
    "parent" : null
  }, {
    "root" : "business",
    "score" : 0.09998228927989707,
    "linkScore" : "NaN",
    "children" : [ {
      "root" : "trade",
      "score" : 0.3188268409399737,
      "linkScore" : 0.9999995764310998,
      "children" : [ ],
      "status" : "none",
      "parent" : null
    }, {
      "root" : "law",
      "score" : 0.10016980397733038,
      "linkScore" : 0.9999884651604047,
      "children" : [ ],
      "status" : "none",
      "parent" : null
    }, {
      "root" : "work",
      "score" : 0.11283027248175495,
      "linkScore" : 0.9999881957034275,
      "children" : [ {
        "root" : "administration",
        "score" : 0.09103231531997089,
        "linkScore" : 0.9999480212941504,
        "children" : [ ],
        "status" : "none",
        "parent" : null
      }, {
        "root" : "care",
        "score" : 0.3682501301146736,
        "linkScore" : 0.9999400602221202,
        "children" : [ {
          "root" : "health care",
          "score" : 1.6034242968227654,
          "linkScore" : 0.9999003667841743,
          "children" : [ ],
          "status" : "none",
          "parent" : null
        } ],
        "status" : "none",
        "parent" : null
      }, {
        "root" : "hard work",
        "score" : 0.14401684967722703,
        "linkScore" : 0.9998929394232469,
        "children" : [ ],
        "status" : "none",
        "parent" : null
      }, {
        "root" : "reform",
        "score" : 0.22074228927610864,
        "linkScore" : 0.9998435865857641,
        "children" : [ ],
        "status" : "none",
        "parent" : null
      }, {
        "root" : "cold war",
        "score" : 0.10656320287899235,
        "linkScore" : 0.9920872828472517,
        "children" : [ ],
        "status" : "none",
        "parent" : null
      } ],
      "status" : "none",
      "parent" : null
    }, {
      "root" : "industry",
      "score" : 0.11600086933010394,
      "linkScore" : 0.9999685926538603,
      "children" : [ {
        "root" : "energy",
        "score" : 0.2990649889631214,
        "linkScore" : 0.44054702461849143,
        "children" : [ {
          "root" : "clean energy",
          "score" : 0.2682391138273491,
          "linkScore" : 0.9938390865450261,
          "children" : [ ],
          "status" : "none",
          "parent" : null
        } ],
        "status" : "none",
        "parent" : null
      } ],
      "status" : "none",
      "parent" : null
    }, {
      "root" : "education",
      "score" : 0.05978977499758562,
      "linkScore" : 0.9999616557773126,
      "children" : [ {
        "root" : "class",
        "score" : 0.35459742111294584,
        "linkScore" : 0.9999477204536142,
        "children" : [ {
          "root" : "person",
          "score" : 0.2917720416619961,
          "linkScore" : 0.999930144331106,
          "children" : [ {
            "root" : "gun",
            "score" : 0.5969353173661267,
            "linkScore" : 0.9999993781675945,
            "children" : [ ],
            "status" : "none",
            "parent" : null
          }, {
            "root" : "inspector",
            "score" : 0.0756159270766884,
            "linkScore" : 0.9999993602060661,
            "children" : [ ],
            "status" : "none",
            "parent" : null
          }, {
            "root" : "success",
            "score" : 0.14447480267152402,
            "linkScore" : 0.9999993498791641,
            "children" : [ ],
            "status" : "none",
            "parent" : null
          }, {
            "root" : "scientist",
            "score" : 0.06565403594261807,
            "linkScore" : 0.999999332451762,
            "children" : [ ],
            "status" : "none",
            "parent" : null
          }, {
            "root" : "enemy",
            "score" : 0.16050714973242675,
            "linkScore" : 0.999999322153317,
            "children" : [ ],
            "status" : "none",
            "parent" : null
          }, {
            "root" : "party",
            "score" : 0.15950539514786138,
            "linkScore" : 0.999999315573209,
            "children" : [ ],
            "status" : "none",
            "parent" : null
          }, {
            "root" : "teacher",
            "score" : 0.10743889930407319,
            "linkScore" : 0.999999280408669,
            "children" : [ ],
            "status" : "none",
            "parent" : null
          }, {
            "root" : "child",
            "score" : 0.1814365659947375,
            "linkScore" : 0.9999992797913477,
            "children" : [ ],
            "status" : "none",
            "parent" : null
          }, {
            "root" : "family",
            "score" : 0.09610040406103279,
            "linkScore" : 0.9999992677390731,
            "children" : [ ],
            "status" : "none",
            "parent" : null
          }, {
            "root" : "terrorist",
            "score" : 0.11734752418194608,
            "linkScore" : 0.9999849229991734,
            "children" : [ ],
            "status" : "none",
            "parent" : null
          }, {
            "root" : "company",
            "score" : 0.2890688781857865,
            "linkScore" : 0.9999828583635957,
            "children" : [ ],
            "status" : "none",
            "parent" : null
          }, {
            "root" : "young person",
            "score" : 0.06717906341275262,
            "linkScore" : 0.9999694681768995,
            "children" : [ ],
            "status" : "none",
            "parent" : null
          }, {
            "root" : "kid",
            "score" : 0.7576586087497874,
            "linkScore" : 0.9999421033217559,
            "children" : [ ],
            "status" : "none",
            "parent" : null
          }, {
            "root" : "terror",
            "score" : 0.3460135783400832,
            "linkScore" : 0.9999234306734078,
            "children" : [ {
              "root" : "war on terror",
              "score" : 0.0956910738354809,
              "linkScore" : 0.9987292718302929,
              "children" : [ ],
              "status" : "none",
              "parent" : null
            }, {
              "root" : "empower",
              "score" : 0.16381791157744474,
              "linkScore" : 0.9183510873013135,
              "children" : [ ],
              "status" : "none",
              "parent" : null
            }, {
              "root" : "year",
              "score" : 0.4770302586577735,
              "linkScore" : 0.9137260583433174,
              "children" : [ ],
              "status" : "none",
              "parent" : null
            }, {
              "root" : "wage",
              "score" : 0.05885227497917692,
              "linkScore" : 0.3188357917170277,
              "children" : [ {
                "root" : "minimum wage",
                "score" : 0.11139770275210167,
                "linkScore" : 0.9999063300390467,
                "children" : [ ],
                "status" : "none",
                "parent" : null
              } ],
              "status" : "none",
              "parent" : null
            } ],
            "status" : "none",
            "parent" : null
          }, {
            "root" : "child care",
            "score" : 0.1610479156697644,
            "linkScore" : 0.9973941217913628,
            "children" : [ ],
            "status" : "none",
            "parent" : null
          }, {
            "root" : "american family",
            "score" : 0.0765037647280104,
            "linkScore" : 0.9802946355493295,
            "children" : [ ],
            "status" : "none",
            "parent" : null
          }, {
            "root" : "american worker",
            "score" : 0.05980751956628244,
            "linkScore" : 0.943822504303294,
            "children" : [ ],
            "status" : "none",
            "parent" : null
          }, {
            "root" : "american person",
            "score" : 0.8503740462249362,
            "linkScore" : 0.8833002205099584,
            "children" : [ ],
            "status" : "none",
            "parent" : null
          } ],
          "status" : "none",
          "parent" : null
        }, {
          "root" : "middle class",
          "score" : 0.15743127900860915,
          "linkScore" : 0.9991859115426707,
          "children" : [ ],
          "status" : "none",
          "parent" : null
        } ],
        "status" : "none",
        "parent" : null
      }, {
        "root" : "school",
        "score" : 0.2092565795384988,
        "linkScore" : 0.9999406402538911,
        "children" : [ {
          "root" : "high school",
          "score" : 0.0737410782416044,
          "linkScore" : 0.9999564813529446,
          "children" : [ ],
          "status" : "none",
          "parent" : null
        } ],
        "status" : "none",
        "parent" : null
      } ],
      "status" : "none",
      "parent" : null
    }, {
      "root" : "weapons of mass",
      "score" : 0.12065814144439653,
      "linkScore" : 0.9272507078923716,
      "children" : [ ],
      "status" : "none",
      "parent" : null
    }, {
      "root" : "weapons of mass destruction",
      "score" : 0.07856419387585789,
      "linkScore" : 0.9265306007746191,
      "children" : [ ],
      "status" : "none",
      "parent" : null
    }, {
      "root" : "trillion",
      "score" : 0.05858247280746053,
      "linkScore" : 0.926253833253338,
      "children" : [ ],
      "status" : "none",
      "parent" : null
    }, {
      "root" : "small business",
      "score" : 0.11039299299458825,
      "linkScore" : 0.9178358359343081,
      "children" : [ ],
      "status" : "none",
      "parent" : null
    }, {
      "root" : "lot",
      "score" : 0.09249441377726028,
      "linkScore" : 0.9122189143916115,
      "children" : [ ],
      "status" : "none",
      "parent" : null
    }, {
      "root" : "rest",
      "score" : 0.08082235498662765,
      "linkScore" : 0.9114950820350587,
      "children" : [ ],
      "status" : "none",
      "parent" : null
    }, {
      "root" : "last year",
      "score" : 0.31789958765893045,
      "linkScore" : 0.6840689615200639,
      "children" : [ ],
      "status" : "none",
      "parent" : null
    }, {
      "root" : "crime",
      "score" : 0.24306615654188196,
      "linkScore" : 0.6533281379046041,
      "children" : [ {
        "root" : "job",
        "score" : 0.2232761343670645,
        "linkScore" : 0.9999976934743949,
        "children" : [ ],
        "status" : "none",
        "parent" : null
      } ],
      "status" : "none",
      "parent" : null
    }, {
      "root" : "community",
      "score" : 0.09733327924815009,
      "linkScore" : 0.6483744019517664,
      "children" : [ ],
      "status" : "none",
      "parent" : null
    }, {
      "root" : "century",
      "score" : 0.08087378774912984,
      "linkScore" : 0.6447474739571286,
      "children" : [ {
        "root" : "st century",
        "score" : 0.7200676132521975,
        "linkScore" : 0.9928088009972533,
        "children" : [ ],
        "status" : "none",
        "parent" : null
      } ],
      "status" : "none",
      "parent" : null
    }, {
      "root" : "surplus",
      "score" : 0.21815703943829864,
      "linkScore" : 0.3160589740512739,
      "children" : [ ],
      "status" : "none",
      "parent" : null
    } ],
    "status" : "none",
    "parent" : null
  }, {
    "root" : "good",
    "score" : 0.06325703611560637,
    "linkScore" : "NaN",
    "children" : [ {
      "root" : "economy",
      "score" : 0.07697496802116174,
      "linkScore" : 0.9999991806989053,
      "children" : [ ],
      "status" : "none",
      "parent" : null
    }, {
      "root" : "welfare",
      "score" : 2.0319866583820914,
      "linkScore" : 0.9999991526745636,
      "children" : [ {
        "root" : "health",
        "score" : 1.0394363662013373,
        "linkScore" : 0.9999436161736062,
        "children" : [ ],
        "status" : "none",
        "parent" : null
      } ],
      "status" : "none",
      "parent" : null
    }, {
      "root" : "women in uniform",
      "score" : 0.05696936614815164,
      "linkScore" : 0.9880343464740915,
      "children" : [ ],
      "status" : "none",
      "parent" : null
    }, {
      "root" : "new economy",
      "score" : 0.15377536662831237,
      "linkScore" : 0.9348559120847294,
      "children" : [ ],
      "status" : "none",
      "parent" : null
    } ],
    "status" : "none",
    "parent" : null
  }, {
    "root" : "five",
    "score" : 0.19068895369920114,
    "linkScore" : "NaN",
    "children" : [ {
      "root" : "american leadership",
      "score" : 0.06622569313155605,
      "linkScore" : 0.9201073493745335,
      "children" : [ ],
      "status" : "none",
      "parent" : null
    }, {
      "root" : "idea",
      "score" : 0.08895375457875457,
      "linkScore" : 0.9185832497189467,
      "children" : [ {
        "root" : "plan",
        "score" : 0.05800227016241641,
        "linkScore" : 0.9986306881492817,
        "children" : [ {
          "root" : "program",
          "score" : 0.09906664951150751,
          "linkScore" : 0.9999361713603412,
          "children" : [ {
            "root" : "regime",
            "score" : 0.7067490493602808,
            "linkScore" : 0.9999979676210874,
            "children" : [ ],
            "status" : "none",
            "parent" : null
          }, {
            "root" : "balanced budget",
            "score" : 0.06837109173682285,
            "linkScore" : 0.9912654306336013,
            "children" : [ ],
            "status" : "none",
            "parent" : null
          }, {
            "root" : "new job",
            "score" : 0.08426458779826788,
            "linkScore" : 0.8414245266025507,
            "children" : [ ],
            "status" : "none",
            "parent" : null
          } ],
          "status" : "none",
          "parent" : null
        }, {
          "root" : "time",
          "score" : 0.12786091890551696,
          "linkScore" : 0.9999358097600849,
          "children" : [ {
            "root" : "first time",
            "score" : 0.0692808076743366,
            "linkScore" : 0.8654992172033454,
            "children" : [ ],
            "status" : "none",
            "parent" : null
          } ],
          "status" : "none",
          "parent" : null
        }, {
          "root" : "recovery plan",
          "score" : 0.060726392802513574,
          "linkScore" : 0.9932276025746952,
          "children" : [ ],
          "status" : "none",
          "parent" : null
        } ],
        "status" : "none",
        "parent" : null
      }, {
        "root" : "way",
        "score" : 0.059893403132181625,
        "linkScore" : 0.9956942678522485,
        "children" : [ ],
        "status" : "none",
        "parent" : null
      }, {
        "root" : "one",
        "score" : 0.113818686285708,
        "linkScore" : 0.9953570204647941,
        "children" : [ ],
        "status" : "none",
        "parent" : null
      }, {
        "root" : "thing",
        "score" : 0.18881656785721845,
        "linkScore" : 0.9921127792936774,
        "children" : [ {
          "root" : "oil",
          "score" : 0.21331444585787712,
          "linkScore" : 0.9999903353060745,
          "children" : [ ],
          "status" : "none",
          "parent" : null
        }, {
          "root" : "world",
          "score" : 0.18964704435000596,
          "linkScore" : 0.9999884723202138,
          "children" : [ ],
          "status" : "none",
          "parent" : null
        }, {
          "root" : "bill",
          "score" : 0.061719436862693294,
          "linkScore" : 0.9999701658096468,
          "children" : [ {
            "root" : "tax",
            "score" : 1.5317754708047233,
            "linkScore" : 0.9999442535150974,
            "children" : [ {
              "root" : "tax relief",
              "score" : 0.12151867785881126,
              "linkScore" : 0.9978414277729153,
              "children" : [ ],
              "status" : "none",
              "parent" : null
            }, {
              "root" : "tax cut",
              "score" : 0.11073096854933877,
              "linkScore" : 0.9816693504859327,
              "children" : [ ],
              "status" : "none",
              "parent" : null
            }, {
              "root" : "tax credit",
              "score" : 0.08530831862385538,
              "linkScore" : 0.865730957662897,
              "children" : [ ],
              "status" : "none",
              "parent" : null
            } ],
            "status" : "none",
            "parent" : null
          }, {
            "root" : "college",
            "score" : 0.22605715363068302,
            "linkScore" : 0.3671335271685593,
            "children" : [ ],
            "status" : "none",
            "parent" : null
          } ],
          "status" : "none",
          "parent" : null
        }, {
          "root" : "drug",
          "score" : 0.08257528489005327,
          "linkScore" : 0.9299652101120672,
          "children" : [ ],
          "status" : "none",
          "parent" : null
        }, {
          "root" : "government",
          "score" : 0.0881858011708216,
          "linkScore" : 0.9230275419685531,
          "children" : [ ],
          "status" : "none",
          "parent" : null
        }, {
          "root" : "price",
          "score" : 0.058045817272045525,
          "linkScore" : 0.9228621418292243,
          "children" : [ ],
          "status" : "none",
          "parent" : null
        }, {
          "root" : "responsibility",
          "score" : 0.10831616830366708,
          "linkScore" : 0.9208843030329436,
          "children" : [ ],
          "status" : "none",
          "parent" : null
        }, {
          "root" : "leadership",
          "score" : 0.07143768410147389,
          "linkScore" : 0.9101188160177942,
          "children" : [ ],
          "status" : "none",
          "parent" : null
        }, {
          "root" : "innovation",
          "score" : 0.058354659887819245,
          "linkScore" : 0.32674972533001456,
          "children" : [ ],
          "status" : "none",
          "parent" : null
        }, {
          "root" : "democracy",
          "score" : 0.06049792313457819,
          "linkScore" : 0.30073738180368265,
          "children" : [ ],
          "status" : "none",
          "parent" : null
        } ],
        "status" : "none",
        "parent" : null
      } ],
      "status" : "none",
      "parent" : null
    }, {
      "root" : "nation",
      "score" : 0.09377671914631461,
      "linkScore" : 0.6712973803643594,
      "children" : [ ],
      "status" : "none",
      "parent" : null
    }, {
      "root" : "economic growth",
      "score" : 0.16027863519159702,
      "linkScore" : 0.3240729018884715,
      "children" : [ ],
      "status" : "none",
      "parent" : null
    } ],
    "status" : "none",
    "parent" : null
  } ],
  "status" : null,
  "parent" : null
}